fwshare/__init__.py
fwshare/basis.py
fwshare/calendar.json
fwshare/cons.py
fwshare/cot.py
fwshare/dailyBar.py
fwshare/receipt.py
fwshare/requests_fun.py
fwshare/rollYield.py
fwshare/sendEmail.py
fwshare/symbolVar.py
fwshare-2.1.3.data/data/fwshare/calendar.json
fwshare-2.1.3.dist-info/METADATA
fwshare-2.1.3.dist-info/WHEEL
fwshare-2.1.3.dist-info/top_level.txt
fwshare-2.1.3.dist-info/RECORD
