Metadata-Version: 2.1
Name: fwshare
Version: 2.1.3
Summary: fwshare
Home-page: https://github.com/18505161903/fwshare
Author: 392161222
Author-email: 392161222@qq.com
License: fwshare
Keywords: pip,fwshare
Platform: any
